_pyagorasdk.cp38-win_amd64.pyd
pyagora.py
PyAgora-0.0.1.data/data/agora_rtc_sdk.dll
PyAgora-0.0.1.data/data/libagora-fdkaac.dll
PyAgora-0.0.1.data/data/libagora-ffmpeg.dll
PyAgora-0.0.1.data/data/libagora-mpg123.dll
PyAgora-0.0.1.data/data/libagora-soundtouch.dll
PyAgora-0.0.1.data/data/libhwcodec.dll
PyAgora-0.0.1.data/data/data/wudao-2-48.wav
PyAgora-0.0.1.data/data/data/wudao.mp4
PyAgora-0.0.1.data/data/example/agora.py
PyAgora-0.0.1.dist-info/METADATA
PyAgora-0.0.1.dist-info/WHEEL
PyAgora-0.0.1.dist-info/top_level.txt
PyAgora-0.0.1.dist-info/RECORD
