Metadata-Version: 2.1
Name: PyAgora
Version: 0.0.1
Summary: AgoraSdk Python Bindings
Home-page: UNKNOWN
Author: Fan
Author-email: UNKNOWN
License: UNKNOWN
Platform: UNKNOWN
